{
  "comforts:sleeping_bag_light_blue": {
    "criteria": {
      "has_the_recipe": "2025-01-23 22:06:31 -0300"
    },
    "done": true
  },
  "naturescompass:natures_compass": {
    "criteria": {
      "has_recipe": "2025-01-23 22:06:31 -0300"
    },
    "done": true
  },
  "comforts:sleeping_bag_black": {
    "criteria": {
      "has_the_recipe": "2025-01-23 22:06:31 -0300"
    },
    "done": true
  },
  "mcwfences:recipes/stone": {
    "criteria": {
      "has_stone": "2025-01-23 22:06:31 -0300"
    },
    "done": true
  },
  "mcwfences:recipes/jungle": {
    "criteria": {
      "has_jungle": "2025-01-23 22:06:31 -0300"
    },
    "done": true
  },
  "mcwfences:recipes/oak": {
    "criteria": {
      "has_oak": "2025-01-23 22:06:31 -0300"
    },
    "done": true
  },
  "mcwfences:recipes/end": {
    "criteria": {
      "has_end_brick": "2025-01-23 22:06:31 -0300"
    },
    "done": true
  },
  "comforts:hammock_purple": {
    "criteria": {
      "has_the_recipe": "2025-01-23 22:06:31 -0300"
    },
    "done": true
  },
  "comforts:hammock_lime": {
    "criteria": {
      "has_the_recipe": "2025-01-23 22:06:31 -0300"
    },
    "done": true
  },
  "comforts:sleeping_bag_pink": {
    "criteria": {
      "has_the_recipe": "2025-01-23 22:06:31 -0300"
    },
    "done": true
  },
  "naturescompass:natures_compass_sapling": {
    "criteria": {
      "has_recipe": "2025-01-23 22:06:31 -0300"
    },
    "done": true
  },
  "comforts:hammock_magenta": {
    "criteria": {
      "has_the_recipe": "2025-01-23 22:06:31 -0300"
    },
    "done": true
  },
  "comforts:sleeping_bag_red": {
    "criteria": {
      "has_the_recipe": "2025-01-23 22:06:31 -0300"
    },
    "done": true
  },
  "comforts:sleeping_bag_orange": {
    "criteria": {
      "has_the_recipe": "2025-01-23 22:06:31 -0300"
    },
    "done": true
  },
  "mcwfences:recipes/bamboo": {
    "criteria": {
      "has_bamboo": "2025-01-23 22:06:31 -0300"
    },
    "done": true
  },
  "comforts:hammock_red": {
    "criteria": {
      "has_the_recipe": "2025-01-23 22:06:31 -0300"
    },
    "done": true
  },
  "comforts:hammock_blue": {
    "criteria": {
      "has_the_recipe": "2025-01-23 22:06:31 -0300"
    },
    "done": true
  },
  "comforts:hammock_white": {
    "criteria": {
      "has_the_recipe": "2025-01-23 22:06:31 -0300"
    },
    "done": true
  },
  "mcwfences:recipes/deepslate": {
    "criteria": {
      "has_deepslate": "2025-01-23 22:06:31 -0300"
    },
    "done": true
  },
  "mcwfences:recipes/mud_brick": {
    "criteria": {
      "has_qq": "2025-01-23 22:06:31 -0300"
    },
    "done": true
  },
  "mcwfences:recipes/mangrove": {
    "criteria": {
      "has_mangrove": "2025-01-23 22:06:31 -0300"
    },
    "done": true
  },
  "mcwfences:recipes/warped": {
    "criteria": {
      "has_warped": "2025-01-23 22:06:31 -0300"
    },
    "done": true
  },
  "comforts:hammock_light_gray": {
    "criteria": {
      "has_the_recipe": "2025-01-23 22:06:31 -0300"
    },
    "done": true
  },
  "comforts:sleeping_bag_white": {
    "criteria": {
      "has_the_recipe": "2025-01-23 22:06:31 -0300"
    },
    "done": true
  },
  "comforts:sleeping_bag_brown": {
    "criteria": {
      "has_the_recipe": "2025-01-23 22:06:31 -0300"
    },
    "done": true
  },
  "comforts:sleeping_bag_gray": {
    "criteria": {
      "has_the_recipe": "2025-01-23 22:06:31 -0300"
    },
    "done": true
  },
  "comforts:rope_and_nail": {
    "criteria": {
      "has_the_recipe": "2025-01-23 22:06:31 -0300"
    },
    "done": true
  },
  "betterdungeons:root": {
    "criteria": {
      "always": "2025-01-23 22:06:31 -0300"
    },
    "done": true
  },
  "mcwfences:recipes/blackstone": {
    "criteria": {
      "has_blackstone": "2025-01-23 22:06:31 -0300"
    },
    "done": true
  },
  "comforts:sleeping_bag_cyan": {
    "criteria": {
      "has_the_recipe": "2025-01-23 22:06:31 -0300"
    },
    "done": true
  },
  "dungeons_arise:wda_root": {
    "criteria": {
      "WDA": "2025-01-23 22:06:31 -0300"
    },
    "done": true
  },
  "mcwfences:recipes/dark_oak": {
    "criteria": {
      "has_dark_oak": "2025-01-23 22:06:31 -0300"
    },
    "done": true
  },
  "comforts:hammock_pink": {
    "criteria": {
      "has_the_recipe": "2025-01-23 22:06:31 -0300"
    },
    "done": true
  },
  "comforts:hammock_brown": {
    "criteria": {
      "has_the_recipe": "2025-01-23 22:06:31 -0300"
    },
    "done": true
  },
  "comforts:sleeping_bag_light_gray": {
    "criteria": {
      "has_the_recipe": "2025-01-23 22:06:31 -0300"
    },
    "done": true
  },
  "comforts:hammock_black": {
    "criteria": {
      "has_the_recipe": "2025-01-23 22:06:31 -0300"
    },
    "done": true
  },
  "comforts:sleeping_bag_lime": {
    "criteria": {
      "has_the_recipe": "2025-01-23 22:06:31 -0300"
    },
    "done": true
  },
  "comforts:hammock_yellow": {
    "criteria": {
      "has_the_recipe": "2025-01-23 22:06:31 -0300"
    },
    "done": true
  },
  "mcwfences:recipes/spruce": {
    "criteria": {
      "has_spruce": "2025-01-23 22:06:31 -0300"
    },
    "done": true
  },
  "mcwfences:recipes/hedge": {
    "criteria": {
      "has_birch": "2025-01-23 22:06:31 -0300"
    },
    "done": true
  },
  "comforts:sleeping_bag_blue": {
    "criteria": {
      "has_the_recipe": "2025-01-23 22:06:31 -0300"
    },
    "done": true
  },
  "mcwfences:recipes/nether": {
    "criteria": {
      "has_nether_brick": "2025-01-23 22:06:31 -0300"
    },
    "done": true
  },
  "mcwfences:recipes/crimson": {
    "criteria": {
      "has_crimson": "2025-01-23 22:06:31 -0300"
    },
    "done": true
  },
  "mcwfences:recipes/prismarine": {
    "criteria": {
      "has_qq": "2025-01-23 22:06:31 -0300"
    },
    "done": true
  },
  "farmersdelight:main/root": {
    "criteria": {
      "seeds": "2025-01-23 22:06:31 -0300"
    },
    "done": true
  },
  "mcwfences:recipes/quartz": {
    "criteria": {
      "has_qq": "2025-01-23 22:06:31 -0300"
    },
    "done": true
  },
  "betterdeserttemples:root": {
    "criteria": {
      "always": "2025-01-23 22:06:31 -0300"
    },
    "done": true
  },
  "naturescompass:natures_compass_log": {
    "criteria": {
      "has_recipe": "2025-01-23 22:06:31 -0300"
    },
    "done": true
  },
  "comforts:hammock_gray": {
    "criteria": {
      "has_the_recipe": "2025-01-23 22:06:31 -0300"
    },
    "done": true
  },
  "mcwfences:recipes/sandstone": {
    "criteria": {
      "has_sand": "2025-01-23 22:06:31 -0300"
    },
    "done": true
  },
  "comforts:hammock_cyan": {
    "criteria": {
      "has_the_recipe": "2025-01-23 22:06:31 -0300"
    },
    "done": true
  },
  "comforts:sleeping_bag_purple": {
    "criteria": {
      "has_the_recipe": "2025-01-23 22:06:31 -0300"
    },
    "done": true
  },
  "comforts:sleeping_bag_yellow": {
    "criteria": {
      "has_the_recipe": "2025-01-23 22:06:31 -0300"
    },
    "done": true
  },
  "mcwfences:recipes/birch": {
    "criteria": {
      "has_birch": "2025-01-23 22:06:31 -0300"
    },
    "done": true
  },
  "comforts:sleeping_bag_green": {
    "criteria": {
      "has_the_recipe": "2025-01-23 22:06:31 -0300"
    },
    "done": true
  },
  "comforts:hammock_light_blue": {
    "criteria": {
      "has_the_recipe": "2025-01-23 22:06:31 -0300"
    },
    "done": true
  },
  "ironfurnaces:coal": {
    "criteria": {
      "rainbowcoal": "2025-01-23 22:06:31 -0300"
    },
    "done": true
  },
  "mcwfences:recipes/acacia": {
    "criteria": {
      "has_acacia": "2025-01-23 22:06:31 -0300"
    },
    "done": true
  },
  "comforts:hammock_orange": {
    "criteria": {
      "has_the_recipe": "2025-01-23 22:06:31 -0300"
    },
    "done": true
  },
  "comforts:sleeping_bag_magenta": {
    "criteria": {
      "has_the_recipe": "2025-01-23 22:06:31 -0300"
    },
    "done": true
  },
  "comforts:hammock_green": {
    "criteria": {
      "has_the_recipe": "2025-01-23 22:06:31 -0300"
    },
    "done": true
  },
  "minecraft:adventure/adventuring_time": {
    "criteria": {
      "minecraft:bamboo_jungle": "2025-01-23 22:16:33 -0300",
      "minecraft:beach": "2025-01-23 22:11:53 -0300",
      "minecraft:sparse_jungle": "2025-01-23 22:09:44 -0300",
      "minecraft:lukewarm_ocean": "2025-01-23 22:12:10 -0300",
      "minecraft:river": "2025-01-23 22:15:31 -0300",
      "minecraft:stony_shore": "2025-01-25 21:47:32 -0300",
      "minecraft:forest": "2025-01-27 17:59:26 -0300",
      "minecraft:lush_caves": "2025-01-24 14:27:27 -0300",
      "minecraft:desert": "2025-01-23 22:16:02 -0300",
      "minecraft:jungle": "2025-01-24 14:10:34 -0300",
      "minecraft:ocean": "2025-01-25 21:49:29 -0300",
      "minecraft:warm_ocean": "2025-01-24 18:37:11 -0300",
      "minecraft:deep_lukewarm_ocean": "2025-01-23 22:14:17 -0300",
      "minecraft:savanna": "2025-01-23 22:06:32 -0300",
      "minecraft:plains": "2025-01-23 22:09:05 -0300"
    },
    "done": false
  },
  "mcwroofs:recipes/acacia": {
    "criteria": {
      "has_planks": "2025-01-23 22:07:35 -0300"
    },
    "done": true
  },
  "minecraft:story/root": {
    "criteria": {
      "crafting_table": "2025-01-23 22:07:43 -0300"
    },
    "done": true
  },
  "mcwroofs:recipes/acacia_planks": {
    "criteria": {
      "has_planks": "2025-01-23 22:07:44 -0300"
    },
    "done": true
  },
  "minecraft:story/mine_stone": {
    "criteria": {
      "get_stone": "2025-01-23 22:08:17 -0300"
    },
    "done": true
  },
  "mcwroofs:recipes/cobblestone": {
    "criteria": {
      "has_planks": "2025-01-23 22:08:17 -0300"
    },
    "done": true
  },
  "minecraft:adventure/root": {
    "criteria": {
      "killed_something": "2025-01-23 22:08:59 -0300"
    },
    "done": true
  },
  "mcwroofs:recipes/awning": {
    "criteria": {
      "has_planks": "2025-01-23 22:08:59 -0300"
    },
    "done": true
  },
  "minecraft:adventure/sleep_in_bed": {
    "criteria": {
      "slept_in_bed": "2025-01-23 22:10:25 -0300"
    },
    "done": true
  },
  "mcwroofs:recipes/jungle": {
    "criteria": {
      "has_planks": "2025-01-23 22:10:41 -0300"
    },
    "done": true
  },
  "minecraft:adventure/kill_all_mobs": {
    "criteria": {
      "minecraft:skeleton": "2025-01-23 22:24:27 -0300",
      "minecraft:ghast": "2025-01-25 19:45:19 -0300",
      "minecraft:spider": "2025-01-23 22:11:22 -0300",
      "minecraft:husk": "2025-01-25 18:45:25 -0300",
      "minecraft:cave_spider": "2025-01-29 14:03:29 -0300",
      "quark:wraith": "2025-01-25 19:53:26 -0300",
      "minecraft:zombie": "2025-01-23 22:33:56 -0300",
      "quark:foxhound": "2025-01-24 18:17:20 -0300",
      "minecraft:drowned": "2025-01-25 18:24:41 -0300"
    },
    "done": false
  },
  "minecraft:adventure/kill_a_mob": {
    "criteria": {
      "minecraft:spider": "2025-01-23 22:11:22 -0300"
    },
    "done": true
  },
  "alexsmobs:alexsmobs/seagull_steal": {
    "criteria": {
      "ex": "2025-01-23 22:11:39 -0300"
    },
    "done": true
  },
  "minecraft:story/obtain_armor": {
    "criteria": {
      "iron_leggings": "2025-01-23 22:13:19 -0300"
    },
    "done": true
  },
  "mcwroofs:recipes/thatch": {
    "criteria": {
      "has_planks": "2025-01-23 22:13:39 -0300"
    },
    "done": true
  },
  "farmersdelight:main/get_fd_seed": {
    "criteria": {
      "tomato_seeds": "2025-01-23 22:13:39 -0300"
    },
    "done": true
  },
  "mcwroofs:recipes/oak": {
    "criteria": {
      "has_planks": "2025-01-23 22:17:18 -0300"
    },
    "done": true
  },
  "minecraft:husbandry/balanced_diet": {
    "criteria": {
      "cooked_mutton": "2025-01-24 17:59:40 -0300",
      "bread": "2025-01-23 22:25:17 -0300",
      "rotten_flesh": "2025-01-25 20:23:27 -0300",
      "glow_berries": "2025-01-24 14:45:09 -0300",
      "melon_slice": "2025-01-24 14:57:32 -0300",
      "mushroom_stew": "2025-01-25 20:08:53 -0300",
      "cooked_salmon": "2025-01-25 18:27:23 -0300"
    },
    "done": false
  },
  "minecraft:husbandry/root": {
    "criteria": {
      "consumed_item": "2025-01-23 22:25:17 -0300"
    },
    "done": true
  },
  "minecraft:story/upgrade_tools": {
    "criteria": {
      "stone_pickaxe": "2025-01-24 13:58:30 -0300"
    },
    "done": true
  },
  "mcwroofs:recipes/granite": {
    "criteria": {
      "has_planks": "2025-01-24 14:20:04 -0300"
    },
    "done": true
  },
  "mcwroofs:recipes/andesite": {
    "criteria": {
      "has_planks": "2025-01-24 14:20:53 -0300"
    },
    "done": true
  },
  "mcwroofs:recipes/diorite": {
    "criteria": {
      "has_planks": "2025-01-24 14:22:02 -0300"
    },
    "done": true
  },
  "mcwroofs:recipes/jungle_planks": {
    "criteria": {
      "has_planks": "2025-01-24 14:33:00 -0300"
    },
    "done": true
  },
  "mcwroofs:recipes/gutters": {
    "criteria": {
      "has_planks": "2025-01-24 14:33:34 -0300"
    },
    "done": true
  },
  "minecraft:story/smelt_iron": {
    "criteria": {
      "iron": "2025-01-24 14:33:34 -0300"
    },
    "done": true
  },
  "minecraft:story/iron_tools": {
    "criteria": {
      "iron_pickaxe": "2025-01-24 14:33:42 -0300"
    },
    "done": true
  },
  "minecraft:story/mine_diamond": {
    "criteria": {
      "diamond": "2025-01-24 14:37:18 -0300"
    },
    "done": true
  },
  "mcwroofs:recipes/stone": {
    "criteria": {
      "has_planks": "2025-01-24 14:46:33 -0300"
    },
    "done": true
  },
  "mcwroofs:recipes/stone_bricks": {
    "criteria": {
      "has_planks": "2025-01-24 14:46:33 -0300"
    },
    "done": true
  },
  "minecraft:story/lava_bucket": {
    "criteria": {
      "lava_bucket": "2025-01-24 17:57:05 -0300"
    },
    "done": true
  },
  "minecraft:nether/root": {
    "criteria": {
      "entered_nether": "2025-01-24 18:09:22 -0300"
    },
    "done": true
  },
  "minecraft:story/enter_the_nether": {
    "criteria": {
      "entered_nether": "2025-01-24 18:09:22 -0300"
    },
    "done": true
  },
  "minecraft:nether/explore_nether": {
    "criteria": {
      "minecraft:crimson_forest": "2025-01-24 18:13:52 -0300",
      "minecraft:nether_wastes": "2025-01-24 18:09:23 -0300",
      "minecraft:soul_sand_valley": "2025-01-25 19:43:19 -0300",
      "minecraft:basalt_deltas": "2025-01-25 19:51:12 -0300"
    },
    "done": false
  },
  "alexsmobs:alexsmobs/crimson_mosquito": {
    "criteria": {
      "killed_by": "2025-01-24 18:14:33 -0300"
    },
    "done": true
  },
  "minecraft:story/form_obsidian": {
    "criteria": {
      "obsidian": "2025-01-24 18:33:47 -0300"
    },
    "done": true
  },
  "alexsmobs:alexsmobs/rattlesnake": {
    "criteria": {
      "interact": "2025-01-24 18:41:37 -0300"
    },
    "done": true
  },
  "farmersdelight:main/plant_all_crops": {
    "criteria": {
      "sugar_cane": "2025-01-24 18:42:43 -0300"
    },
    "done": false
  },
  "mcwroofs:recipes/concrete": {
    "criteria": {
      "has_planks": "2025-01-24 18:43:22 -0300"
    },
    "done": true
  },
  "betterdungeons:all_dungeons": {
    "criteria": {
      "in_better_zombie_dungeon": "2025-01-25 18:34:14 -0300",
      "in_better_spider_dungeon": "2025-01-29 13:20:16 -0300"
    },
    "done": false
  },
  "betterdungeons:zombie_dungeon": {
    "criteria": {
      "in_better_zombie_dungeon": "2025-01-25 18:34:14 -0300"
    },
    "done": true
  },
  "minecraft:husbandry/bred_all_animals": {
    "criteria": {
      "minecraft:ocelot": "2025-01-25 18:37:32 -0300"
    },
    "done": false
  },
  "minecraft:husbandry/breed_an_animal": {
    "criteria": {
      "bred": "2025-01-25 18:37:32 -0300"
    },
    "done": true
  },
  "alexsmobs:alexsmobs/guster": {
    "criteria": {
      "killed_by": "2025-01-25 18:55:36 -0300"
    },
    "done": true
  },
  "alexsmobs:alexsmobs/root": {
    "criteria": {
      "useitem": "2025-01-25 19:32:15 -0300"
    },
    "done": true
  },
  "minecraft:adventure/shoot_arrow": {
    "criteria": {
      "shot_arrow": "2025-01-25 19:42:49 -0300"
    },
    "done": true
  },
  "farmersdelight:main/eat_comfort_food": {
    "criteria": {
      "comfort": "2025-01-25 20:08:53 -0300"
    },
    "done": true
  },
  "minecraft:nether/obtain_crying_obsidian": {
    "criteria": {
      "crying_obsidian": "2025-01-25 21:52:32 -0300"
    },
    "done": true
  },
  "minecraft:nether/return_to_sender": {
    "criteria": {
      "killed_ghast": "2025-01-27 18:15:33 -0300"
    },
    "done": true
  },
  "minecraft:husbandry/tame_an_animal": {
    "criteria": {
      "tamed_animal": "2025-01-27 18:31:40 -0300"
    },
    "done": true
  },
  "betterdungeons:spider_dungeon": {
    "criteria": {
      "in_better_spider_dungeon": "2025-01-29 13:20:16 -0300"
    },
    "done": true
  },
  "farmersdelight:recipes/cooking/dog_food": {
    "criteria": {
      "has_any_ingredient": "2025-01-31 22:56:40 -0300"
    },
    "done": true
  },
  "securitycraft:recipes/misc/sentry": {
    "criteria": {
      "has_iron": "2025-01-31 23:00:50 -0300"
    },
    "done": true
  },
  "mcwbridges:recipes/rope_jungle_bridge": {
    "criteria": {
      "has_planks": "2025-01-31 23:14:00 -0300"
    },
    "done": true
  },
  "farmersdelight:recipes/food/nether_salad": {
    "criteria": {
      "has_bowl": "2025-01-31 22:56:40 -0300"
    },
    "done": true
  },
  "minecraft:recipes/combat/leather_helmet": {
    "criteria": {
      "has_leather": "2025-01-31 22:56:40 -0300"
    },
    "done": true
  },
  "minecraft:recipes/misc/melon_seeds": {
    "criteria": {
      "has_melon": "2025-01-31 22:56:40 -0300"
    },
    "done": true
  },
  "minecraft:recipes/decorations/ladder": {
    "criteria": {
      "has_stick": "2025-01-31 22:56:40 -0300"
    },
    "done": true
  },
  "securitycraft:recipes/building_blocks/reinforced_mossy_stone_bricks_from_vine": {
    "criteria": {
      "has_vine": "2025-01-31 22:56:40 -0300"
    },
    "done": true
  },
  "minecraft:recipes/combat/iron_leggings": {
    "criteria": {
      "has_iron_ingot": "2025-01-31 23:00:50 -0300"
    },
    "done": true
  },
  "farmersdelight:recipes/food/melon_juice": {
    "criteria": {
      "has_melon_slice": "2025-01-31 22:56:40 -0300"
    },
    "done": true
  },
  "minecraft:recipes/combat/leather_leggings": {
    "criteria": {
      "has_leather": "2025-01-31 22:56:40 -0300"
    },
    "done": true
  },
  "securitycraft:recipes/redstone/reinforced_birch_fence_gate": {
    "criteria": {
      "has_stick": "2025-01-31 22:56:40 -0300"
    },
    "done": true
  },
  "securitycraft:recipes/redstone/reinforced_crimson_fence_gate": {
    "criteria": {
      "has_stick": "2025-01-31 22:56:40 -0300"
    },
    "done": true
  },
  "mcwbridges:recipes/jungle_log_bridge_middle": {
    "criteria": {
      "has_planks": "2025-01-31 23:14:00 -0300"
    },
    "done": true
  },
  "securitycraft:recipes/misc/motion_activated_light": {
    "criteria": {
      "has_stick": "2025-01-31 22:56:40 -0300"
    },
    "done": true
  },
  "securitycraft:recipes/redstone/reinforced_jungle_fence_gate": {
    "criteria": {
      "has_stick": "2025-01-31 22:56:40 -0300"
    },
    "done": true
  },
  "minecraft:recipes/misc/iron_nugget_from_smelting": {
    "criteria": {
      "has_iron_shovel": "2025-01-31 22:56:40 -0300"
    },
    "done": true
  },
  "securitycraft:recipes/misc/blacklist_module": {
    "criteria": {
      "has_iron": "2025-01-31 23:00:50 -0300"
    },
    "done": true
  },
  "minecraft:recipes/building_blocks/mossy_stone_bricks_from_vine": {
    "criteria": {
      "has_vine": "2025-01-31 22:56:40 -0300"
    },
    "done": true
  },
  "minecraft:recipes/building_blocks/quartz_slab": {
    "criteria": {
      "has_quartz_block": "2025-01-31 22:58:42 -0300"
    },
    "done": true
  },
  "mcwtrpdoors:recipes/acacia/jungle_bark_trapdoor": {
    "criteria": {
      "has_logs": "2025-01-31 22:56:40 -0300"
    },
    "done": true
  },
  "minecraft:recipes/building_blocks/jungle_wood": {
    "criteria": {
      "has_log": "2025-01-31 22:56:40 -0300"
    },
    "done": true
  },
  "securitycraft:recipes/building_blocks/secret_birch_sign_item": {
    "criteria": {
      "has_sign": "2025-01-31 22:56:40 -0300"
    },
    "done": true
  },
  "mcwtrpdoors:recipes/metal/metal_warning_trapdoor": {
    "criteria": {
      "has_logs": "2025-01-31 23:00:50 -0300"
    },
    "done": true
  },
  "minecraft:recipes/combat/iron_chestplate": {
    "criteria": {
      "has_iron_ingot": "2025-01-31 23:00:50 -0300"
    },
    "done": true
  },
  "minecraft:recipes/building_blocks/quartz_bricks": {
    "criteria": {
      "has_quartz_block": "2025-01-31 22:58:42 -0300"
    },
    "done": true
  },
  "mcwtrpdoors:recipes/bamboo/bamboo_barred_trapdoor": {
    "criteria": {
      "has_logs": "2025-01-31 22:56:40 -0300"
    },
    "done": true
  },
  "minecraft:recipes/misc/gold_nugget_from_smelting": {
    "criteria": {
      "has_golden_hoe": "2025-01-31 22:56:40 -0300"
    },
    "done": true
  },
  "mcwtrpdoors:recipes/jungle/jungle_cottage_trapdoor": {
    "criteria": {
      "has_logs": "2025-01-31 22:56:40 -0300"
    },
    "done": true
  },
  "securitycraft:recipes/misc/limited_use_keycard": {
    "criteria": {
      "has_iron": "2025-01-31 23:00:50 -0300"
    },
    "done": true
  },
  "securitycraft:recipes/misc/bouncing_betty": {
    "criteria": {
      "has_iron": "2025-01-31 23:00:50 -0300"
    },
    "done": true
  },
  "minecraft:recipes/misc/iron_nugget": {
    "criteria": {
      "has_iron_ingot": "2025-01-31 23:00:50 -0300"
    },
    "done": true
  },
  "farmersdelight:recipes/combat/flint_knife": {
    "criteria": {
      "has_stick": "2025-01-31 22:56:40 -0300"
    },
    "done": true
  },
  "mcwdoors:recipes/jungle": {
    "criteria": {
      "has_wood": "2025-01-31 22:56:40 -0300"
    },
    "done": true
  },
  "minecraft:recipes/misc/bucket": {
    "criteria": {
      "has_iron_ingot": "2025-01-31 23:00:50 -0300"
    },
    "done": true
  },
  "securitycraft:recipes/misc/disguise_module": {
    "criteria": {
      "has_iron": "2025-01-31 23:00:50 -0300"
    },
    "done": true
  },
  "securitycraft:recipes/building_blocks/secret_mangrove_hanging_sign": {
    "criteria": {
      "has_sign": "2025-01-31 22:56:40 -0300"
    },
    "done": true
  },
  "minecraft:recipes/combat/iron_helmet": {
    "criteria": {
      "has_iron_ingot": "2025-01-31 23:00:50 -0300"
    },
    "done": true
  },
  "minecraft:recipes/transportation/minecart": {
    "criteria": {
      "has_iron_ingot": "2025-01-31 23:00:50 -0300"
    },
    "done": true
  },
  "minecraft:recipes/tools/iron_hoe": {
    "criteria": {
      "has_iron_ingot": "2025-01-31 23:00:50 -0300"
    },
    "done": true
  },
  "mcwbridges:recipes/dry_bamboo_bridge": {
    "criteria": {
      "has_planks": "2025-01-31 22:56:40 -0300"
    },
    "done": true
  },
  "mcwtrpdoors:recipes/jungle/jungle_swamp_trapdoor": {
    "criteria": {
      "has_logs": "2025-01-31 22:56:40 -0300"
    },
    "done": true
  },
  "farmersdelight:recipes/food/melon_popsicle": {
    "criteria": {
      "has_melon": "2025-01-31 22:56:40 -0300"
    },
    "done": true
  },
  "securitycraft:recipes/building_blocks/secret_warped_sign_item": {
    "criteria": {
      "has_sign": "2025-01-31 22:56:40 -0300"
    },
    "done": true
  },
  "minecraft:recipes/tools/wooden_axe": {
    "criteria": {
      "has_stick": "2025-01-31 22:56:40 -0300"
    },
    "done": true
  },
  "securitycraft:recipes/redstone/block_change_detector": {
    "criteria": {
      "has_iron": "2025-01-31 23:00:50 -0300"
    },
    "done": true
  },
  "minecraft:recipes/misc/gold_nugget_from_blasting": {
    "criteria": {
      "has_golden_hoe": "2025-01-31 22:56:40 -0300"
    },
    "done": true
  },
  "securitycraft:recipes/decorations/floor_trap": {
    "criteria": {
      "has_iron": "2025-01-31 23:00:50 -0300"
    },
    "done": true
  },
  "securitycraft:recipes/building_blocks/secret_birch_hanging_sign": {
    "criteria": {
      "has_sign": "2025-01-31 22:56:40 -0300"
    },
    "done": true
  },
  "minecraft:recipes/combat/leather_chestplate": {
    "criteria": {
      "has_leather": "2025-01-31 22:56:40 -0300"
    },
    "done": true
  },
  "securitycraft:recipes/redstone/reinforced_spruce_fence_gate": {
    "criteria": {
      "has_stick": "2025-01-31 22:56:40 -0300"
    },
    "done": true
  },
  "mcwtrpdoors:recipes/bamboo/bamboo_glass_trapdoor": {
    "criteria": {
      "has_logs": "2025-01-31 22:56:40 -0300"
    },
    "done": true
  },
  "mcwlights:recipes/lava_lamp": {
    "criteria": {
      "has_wood": "2025-01-31 23:00:50 -0300"
    },
    "done": true
  },
  "minecraft:recipes/decorations/crafting_table": {
    "criteria": {
      "unlock_right_away": "2025-01-31 22:56:40 -0300"
    },
    "done": true
  },
  "securitycraft:recipes/misc/storage_module": {
    "criteria": {
      "has_iron": "2025-01-31 23:00:50 -0300"
    },
    "done": true
  },
  "minecraft:recipes/decorations/chest": {
    "criteria": {
      "has_lots_of_items": "2025-01-31 22:56:40 -0300"
    },
    "done": true
  },
  "minecraft:recipes/tools/shears": {
    "criteria": {
      "has_iron_ingot": "2025-01-31 23:00:50 -0300"
    },
    "done": true
  },
  "minecraft:recipes/misc/stick": {
    "criteria": {
      "has_planks": "2025-01-31 23:14:00 -0300"
    },
    "done": true
  },
  "securitycraft:recipes/misc/reinforced_jungle_fence": {
    "criteria": {
      "has_stick": "2025-01-31 22:56:40 -0300"
    },
    "done": true
  },
  "securitycraft:recipes/building_blocks/secret_warped_hanging_sign": {
    "criteria": {
      "has_sign": "2025-01-31 22:56:40 -0300"
    },
    "done": true
  },
  "minecraft:recipes/transportation/cherry_boat": {
    "criteria": {
      "in_water": "2025-01-31 22:57:37 -0300"
    },
    "done": true
  },
  "mcwbridges:recipes/dry_bamboo_bridge_pier": {
    "criteria": {
      "has_planks": "2025-01-31 22:56:40 -0300"
    },
    "done": true
  },
  "securitycraft:recipes/building_blocks/secret_jungle_hanging_sign": {
    "criteria": {
      "has_sign": "2025-01-31 22:56:40 -0300"
    },
    "done": true
  },
  "minecraft:recipes/building_blocks/quartz_pillar_from_quartz_block_stonecutting": {
    "criteria": {
      "has_quartz_block": "2025-01-31 22:58:42 -0300"
    },
    "done": true
  },
  "minecraft:recipes/decorations/chain": {
    "criteria": {
      "has_iron_ingot": "2025-01-31 23:00:50 -0300"
    },
    "done": true
  },
  "mcwtrpdoors:recipes/jungle/jungle_ranch_trapdoor": {
    "criteria": {
      "has_logs": "2025-01-31 22:56:40 -0300"
    },
    "done": true
  },
  "securitycraft:recipes/misc/reinforced_warped_fence": {
    "criteria": {
      "has_stick": "2025-01-31 22:56:40 -0300"
    },
    "done": true
  },
  "minecraft:recipes/building_blocks/iron_block": {
    "criteria": {
      "has_iron_ingot": "2025-01-31 23:00:50 -0300"
    },
    "done": true
  },
  "minecraft:recipes/misc/bone_meal": {
    "criteria": {
      "has_bone": "2025-01-31 22:56:40 -0300"
    },
    "done": true
  },
  "farmersdelight:recipes/decorations/cooking_pot": {
    "criteria": {
      "has_iron_ingot": "2025-01-31 23:00:50 -0300"
    },
    "done": true
  },
  "mcwtrpdoors:recipes/bamboo/bamboo_cottage_trapdoor": {
    "criteria": {
      "has_logs": "2025-01-31 22:56:40 -0300"
    },
    "done": true
  },
  "mcwtrpdoors:recipes/metal/metal_trapdoor": {
    "criteria": {
      "has_logs": "2025-01-31 23:00:50 -0300"
    },
    "done": true
  },
  "mcwtrpdoors:recipes/bamboo/bamboo_four_panel_trapdoor": {
    "criteria": {
      "has_logs": "2025-01-31 22:56:40 -0300"
    },
    "done": true
  },
  "minecraft:recipes/transportation/bamboo_raft": {
    "criteria": {
      "in_water": "2025-01-31 22:57:37 -0300"
    },
    "done": true
  },
  "minecraft:recipes/decorations/smithing_table": {
    "criteria": {
      "has_iron_ingot": "2025-01-31 23:00:50 -0300"
    },
    "done": true
  },
  "securitycraft:recipes/transportation/track_mine": {
    "criteria": {
      "has_iron": "2025-01-31 23:00:50 -0300"
    },
    "done": true
  },
  "securitycraft:recipes/building_blocks/secret_cherry_hanging_sign": {
    "criteria": {
      "has_sign": "2025-01-31 22:56:40 -0300"
    },
    "done": true
  },
  "securitycraft:recipes/building_blocks/secret_dark_oak_sign_item": {
    "criteria": {
      "has_sign": "2025-01-31 22:56:40 -0300"
    },
    "done": true
  },
  "securitycraft:recipes/building_blocks/secret_dark_oak_hanging_sign": {
    "criteria": {
      "has_sign": "2025-01-31 22:56:40 -0300"
    },
    "done": true
  },
  "minecraft:recipes/building_blocks/quartz_pillar": {
    "criteria": {
      "has_quartz_block": "2025-01-31 22:58:42 -0300"
    },
    "done": true
  },
  "minecraft:recipes/transportation/spruce_boat": {
    "criteria": {
      "in_water": "2025-01-31 22:57:37 -0300"
    },
    "done": true
  },
  "minecraft:recipes/building_blocks/quartz_stairs_from_quartz_block_stonecutting": {
    "criteria": {
      "has_quartz_block": "2025-01-31 22:58:42 -0300"
    },
    "done": true
  },
  "securitycraft:recipes/redstone/reinforced_cherry_fence_gate": {
    "criteria": {
      "has_stick": "2025-01-31 22:56:40 -0300"
    },
    "done": true
  },
  "minecraft:recipes/redstone/jungle_button": {
    "criteria": {
      "has_planks": "2025-01-31 23:14:00 -0300"
    },
    "done": true
  },
  "minecraft:recipes/misc/leather_horse_armor": {
    "criteria": {
      "has_leather": "2025-01-31 22:56:40 -0300"
    },
    "done": true
  },
  "securitycraft:recipes/misc/whitelist_module": {
    "criteria": {
      "has_iron": "2025-01-31 23:00:50 -0300"
    },
    "done": true
  },
  "minecraft:recipes/transportation/birch_boat": {
    "criteria": {
      "in_water": "2025-01-31 22:57:37 -0300"
    },
    "done": true
  },
  "securitycraft:recipes/building_blocks/secret_mangrove_sign_item": {
    "criteria": {
      "has_sign": "2025-01-31 22:56:40 -0300"
    },
    "done": true
  },
  "minecraft:recipes/transportation/oak_boat": {
    "criteria": {
      "in_water": "2025-01-31 22:57:37 -0300"
    },
    "done": true
  },
  "securitycraft:recipes/misc/reinforced_acacia_fence": {
    "criteria": {
      "has_stick": "2025-01-31 22:56:40 -0300"
    },
    "done": true
  },
  "securitycraft:recipes/building_blocks/reinforced_mossy_cobblestone_from_vine": {
    "criteria": {
      "has_vine": "2025-01-31 22:56:40 -0300"
    },
    "done": true
  },
  "securitycraft:recipes/building_blocks/secret_crimson_sign_item": {
    "criteria": {
      "has_sign": "2025-01-31 22:56:40 -0300"
    },
    "done": true
  },
  "mcwbridges:recipes/iron_bridge_pier": {
    "criteria": {
      "has_planks": "2025-01-31 23:00:50 -0300"
    },
    "done": true
  },
  "mcwtrpdoors:recipes/jungle/jungle_barn_trapdoor": {
    "criteria": {
      "has_logs": "2025-01-31 22:56:40 -0300"
    },
    "done": true
  },
  "securitycraft:recipes/redstone/reinforced_acacia_fence_gate": {
    "criteria": {
      "has_stick": "2025-01-31 22:56:40 -0300"
    },
    "done": true
  },
  "mcwtrpdoors:recipes/bamboo/bamboo_paper_trapdoor": {
    "criteria": {
      "has_logs": "2025-01-31 22:56:40 -0300"
    },
    "done": true
  },
  "minecraft:recipes/building_blocks/mossy_cobblestone_from_vine": {
    "criteria": {
      "has_vine": "2025-01-31 22:56:40 -0300"
    },
    "done": true
  },
  "mcwtrpdoors:recipes/jungle/jungle_four_panel_trapdoor": {
    "criteria": {
      "has_logs": "2025-01-31 22:56:40 -0300"
    },
    "done": true
  },
  "securitycraft:recipes/building_blocks/secret_acacia_sign_item": {
    "criteria": {
      "has_sign": "2025-01-31 22:56:40 -0300"
    },
    "done": true
  },
  "minecraft:recipes/building_blocks/jungle_stairs": {
    "criteria": {
      "has_planks": "2025-01-31 23:14:00 -0300"
    },
    "done": true
  },
  "securitycraft:recipes/misc/security_camera": {
    "criteria": {
      "has_iron": "2025-01-31 23:00:50 -0300"
    },
    "done": true
  },
  "minecraft:recipes/redstone/jungle_fence_gate": {
    "criteria": {
      "has_planks": "2025-01-31 23:14:00 -0300"
    },
    "done": true
  },
  "securitycraft:recipes/redstone/reinforced_dispenser": {
    "criteria": {
      "has_bow": "2025-01-31 22:56:40 -0300"
    },
    "done": true
  },
  "mcwbridges:recipes/jungle_bridge_pier": {
    "criteria": {
      "has_planks": "2025-01-31 22:56:40 -0300"
    },
    "done": true
  },
  "mcwtrpdoors:recipes/print_beach": {
    "criteria": {
      "has_logs": "2025-01-31 22:56:40 -0300"
    },
    "done": true
  },
  "minecraft:recipes/combat/iron_sword": {
    "criteria": {
      "has_iron_ingot": "2025-01-31 23:00:50 -0300"
    },
    "done": true
  },
  "minecraft:recipes/tools/iron_pickaxe": {
    "criteria": {
      "has_iron_ingot": "2025-01-31 23:00:50 -0300"
    },
    "done": true
  },
  "mcwtrpdoors:recipes/bamboo/bamboo_barn_trapdoor": {
    "criteria": {
      "has_logs": "2025-01-31 22:56:40 -0300"
    },
    "done": true
  },
  "minecraft:recipes/transportation/mangrove_boat": {
    "criteria": {
      "in_water": "2025-01-31 22:57:37 -0300"
    },
    "done": true
  },
  "minecraft:recipes/decorations/torch": {
    "criteria": {
      "has_stone_pickaxe": "2025-01-31 22:56:40 -0300"
    },
    "done": true
  },
  "minecraft:recipes/combat/shield": {
    "criteria": {
      "has_iron_ingot": "2025-01-31 23:00:50 -0300"
    },
    "done": true
  },
  "minecraft:recipes/redstone/hopper": {
    "criteria": {
      "has_iron_ingot": "2025-01-31 23:00:50 -0300"
    },
    "done": true
  },
  "securitycraft:recipes/misc/reinforced_cherry_fence": {
    "criteria": {
      "has_stick": "2025-01-31 22:56:40 -0300"
    },
    "done": true
  },
  "minecraft:recipes/decorations/iron_bars": {
    "criteria": {
      "has_iron_ingot": "2025-01-31 23:00:50 -0300"
    },
    "done": true
  },
  "securitycraft:recipes/misc/briefcase": {
    "criteria": {
      "has_iron": "2025-01-31 23:00:50 -0300"
    },
    "done": true
  },
  "mcwtrpdoors:recipes/bamboo/bamboo_barrel_trapdoor": {
    "criteria": {
      "has_logs": "2025-01-31 22:56:40 -0300"
    },
    "done": true
  },
  "trashcans:recipes/misc/liquid_trash_can": {
    "criteria": {
      "recipe_condition": "2025-01-31 22:56:40 -0300"
    },
    "done": true
  },
  "mcwtrpdoors:recipes/bamboo/bamboo_tropical_trapdoor": {
    "criteria": {
      "has_logs": "2025-01-31 22:56:40 -0300"
    },
    "done": true
  },
  "securitycraft:recipes/redstone/reinforced_bamboo_fence_gate": {
    "criteria": {
      "has_stick": "2025-01-31 22:56:40 -0300"
    },
    "done": true
  },
  "securitycraft:recipes/redstone/reinforced_fence_gate": {
    "criteria": {
      "has_iron": "2025-01-31 23:00:50 -0300"
    },
    "done": true
  },
  "minecraft:recipes/building_blocks/quartz_stairs": {
    "criteria": {
      "has_quartz_block": "2025-01-31 22:58:42 -0300"
    },
    "done": true
  },
  "mcwtrpdoors:recipes/bamboo/bamboo_swamp_trapdoor": {
    "criteria": {
      "has_logs": "2025-01-31 22:56:40 -0300"
    },
    "done": true
  },
  "sophisticatedbackpacks:recipes/misc/backpack": {
    "criteria": {
      "has_leather": "2025-01-31 22:56:40 -0300"
    },
    "done": true
  },
  "minecraft:recipes/brewing/glistering_melon_slice": {
    "criteria": {
      "has_melon": "2025-01-31 22:56:40 -0300"
    },
    "done": true
  },
  "minecraft:recipes/building_blocks/smooth_quartz": {
    "criteria": {
      "has_quartz_block": "2025-01-31 22:58:42 -0300"
    },
    "done": true
  },
  "securitycraft:recipes/building_blocks/secret_bamboo_hanging_sign": {
    "criteria": {
      "has_sign": "2025-01-31 22:56:40 -0300"
    },
    "done": true
  },
  "mcwbridges:recipes/jungle_rail_bridge": {
    "criteria": {
      "has_planks": "2025-01-31 23:14:00 -0300"
    },
    "done": true
  },
  "securitycraft:recipes/misc/electrified_iron_fence": {
    "criteria": {
      "has_iron": "2025-01-31 23:00:50 -0300"
    },
    "done": true
  },
  "mcwtrpdoors:recipes/jungle/jungle_tropical_trapdoor": {
    "criteria": {
      "has_logs": "2025-01-31 22:56:40 -0300"
    },
    "done": true
  },
  "securitycraft:recipes/redstone/reinforced_warped_fence_gate": {
    "criteria": {
      "has_stick": "2025-01-31 22:56:40 -0300"
    },
    "done": true
  },
  "securitycraft:recipes/misc/keycard_lv5": {
    "criteria": {
      "has_iron": "2025-01-31 23:00:50 -0300"
    },
    "done": true
  },
  "securitycraft:recipes/misc/keycard_lv3": {
    "criteria": {
      "has_iron": "2025-01-31 23:00:50 -0300"
    },
    "done": true
  },
  "securitycraft:recipes/misc/keycard_lv4": {
    "criteria": {
      "has_iron": "2025-01-31 23:00:50 -0300"
    },
    "done": true
  },
  "securitycraft:recipes/misc/keycard_lv1": {
    "criteria": {
      "has_iron": "2025-01-31 23:00:50 -0300"
    },
    "done": true
  },
  "securitycraft:recipes/misc/keycard_lv2": {
    "criteria": {
      "has_iron": "2025-01-31 23:00:50 -0300"
    },
    "done": true
  },
  "minecraft:recipes/building_blocks/jungle_planks": {
    "criteria": {
      "has_logs": "2025-01-31 22:56:40 -0300"
    },
    "done": true
  },
  "minecraft:recipes/combat/iron_boots": {
    "criteria": {
      "has_iron_ingot": "2025-01-31 23:00:50 -0300"
    },
    "done": true
  },
  "minecraft:recipes/building_blocks/chiseled_quartz_block": {
    "criteria": {
      "has_quartz_block": "2025-01-31 22:58:42 -0300"
    },
    "done": true
  },
  "securitycraft:recipes/building_blocks/secret_crimson_hanging_sign": {
    "criteria": {
      "has_sign": "2025-01-31 22:56:40 -0300"
    },
    "done": true
  },
  "mcwtrpdoors:recipes/jungle/jungle_glass_trapdoor": {
    "criteria": {
      "has_logs": "2025-01-31 22:56:40 -0300"
    },
    "done": true
  },
  "minecraft:recipes/brewing/fermented_spider_eye": {
    "criteria": {
      "has_spider_eye": "2025-01-31 22:56:40 -0300"
    },
    "done": true
  },
  "mcwtrpdoors:recipes/bamboo/bamboo_classic_trapdoor": {
    "criteria": {
      "has_logs": "2025-01-31 22:56:40 -0300"
    },
    "done": true
  },
  "mcwlights:recipes/paper_lamp": {
    "criteria": {
      "has_wood": "2025-01-31 22:56:40 -0300"
    },
    "done": true
  },
  "minecraft:recipes/building_blocks/quartz_bricks_from_quartz_block_stonecutting": {
    "criteria": {
      "has_quartz_block": "2025-01-31 22:58:42 -0300"
    },
    "done": true
  },
  "mcwtrpdoors:recipes/jungle/jungle_classic_trapdoor": {
    "criteria": {
      "has_logs": "2025-01-31 22:56:40 -0300"
    },
    "done": true
  },
  "minecraft:recipes/decorations/lantern": {
    "criteria": {
      "has_iron_ingot": "2025-01-31 23:00:50 -0300"
    },
    "done": true
  },
  "securitycraft:recipes/building_blocks/secret_cherry_sign_item": {
    "criteria": {
      "has_sign": "2025-01-31 22:56:40 -0300"
    },
    "done": true
  },
  "trashcans:recipes/misc/item_trash_can": {
    "criteria": {
      "recipe_condition": "2025-01-31 23:14:10 -0300"
    },
    "done": true
  },
  "securitycraft:recipes/misc/mine": {
    "criteria": {
      "has_iron": "2025-01-31 23:00:50 -0300"
    },
    "done": true
  },
  "minecraft:recipes/decorations/campfire": {
    "criteria": {
      "has_stick": "2025-01-31 22:56:40 -0300"
    },
    "done": true
  },
  "minecraft:recipes/redstone/jungle_trapdoor": {
    "criteria": {
      "has_planks": "2025-01-31 23:14:00 -0300"
    },
    "done": true
  },
  "minecraft:recipes/tools/wooden_hoe": {
    "criteria": {
      "has_stick": "2025-01-31 22:56:40 -0300"
    },
    "done": true
  },
  "securitycraft:recipes/misc/harming_module": {
    "criteria": {
      "has_iron": "2025-01-31 23:00:50 -0300"
    },
    "done": true
  },
  "minecraft:recipes/misc/charcoal": {
    "criteria": {
      "has_log": "2025-01-31 22:56:40 -0300"
    },
    "done": true
  },
  "minecraft:recipes/tools/wooden_pickaxe": {
    "criteria": {
      "has_stick": "2025-01-31 22:56:40 -0300"
    },
    "done": true
  },
  "minecraft:recipes/tools/iron_shovel": {
    "criteria": {
      "has_iron_ingot": "2025-01-31 23:00:50 -0300"
    },
    "done": true
  },
  "minecraft:recipes/decorations/item_frame": {
    "criteria": {
      "has_leather": "2025-01-31 22:56:40 -0300"
    },
    "done": true
  },
  "farmersdelight:recipes/food/mixed_salad": {
    "criteria": {
      "has_bowl": "2025-01-31 22:56:40 -0300"
    },
    "done": true
  },
  "mcwdoors:recipes/metal": {
    "criteria": {
      "has_wood": "2025-01-31 23:00:50 -0300"
    },
    "done": true
  },
  "securitycraft:recipes/misc/sonic_security_system": {
    "criteria": {
      "has_stick": "2025-01-31 22:56:40 -0300"
    },
    "done": true
  },
  "farmersdelight:recipes/cooking/bone_broth": {
    "criteria": {
      "has_bone": "2025-01-31 22:56:40 -0300"
    },
    "done": true
  },
  "mcwbridges:recipes/bamboo_bridge": {
    "criteria": {
      "has_planks": "2025-01-31 22:56:40 -0300"
    },
    "done": true
  },
  "minecraft:recipes/decorations/jungle_sign": {
    "criteria": {
      "has_planks": "2025-01-31 23:14:00 -0300"
    },
    "done": true
  },
  "sophisticatedbackpacks:recipes/misc/upgrade_base": {
    "criteria": {
      "has_leather": "2025-01-31 22:56:40 -0300"
    },
    "done": true
  },
  "securitycraft:recipes/misc/smart_module": {
    "criteria": {
      "has_iron": "2025-01-31 23:00:50 -0300"
    },
    "done": true
  },
  "mcwtrpdoors:recipes/jungle/jungle_mystic_trapdoor": {
    "criteria": {
      "has_logs": "2025-01-31 22:56:40 -0300"
    },
    "done": true
  },
  "securitycraft:recipes/redstone/reinforced_mangrove_fence_gate": {
    "criteria": {
      "has_stick": "2025-01-31 22:56:40 -0300"
    },
    "done": true
  },
  "minecraft:recipes/redstone/jungle_door": {
    "criteria": {
      "has_planks": "2025-01-31 23:14:00 -0300"
    },
    "done": true
  },
  "minecraft:recipes/building_blocks/melon": {
    "criteria": {
      "has_melon": "2025-01-31 22:56:40 -0300"
    },
    "done": true
  },
  "mcwtrpdoors:recipes/metal/metal_full_trapdoor": {
    "criteria": {
      "has_logs": "2025-01-31 23:00:50 -0300"
    },
    "done": true
  },
  "minecraft:recipes/tools/wooden_shovel": {
    "criteria": {
      "has_stick": "2025-01-31 22:56:40 -0300"
    },
    "done": true
  },
  "securitycraft:recipes/misc/reinforced_mangrove_fence": {
    "criteria": {
      "has_stick": "2025-01-31 22:56:40 -0300"
    },
    "done": true
  },
  "mcwtrpdoors:recipes/jungle/jungle_barrel_trapdoor": {
    "criteria": {
      "has_logs": "2025-01-31 22:56:40 -0300"
    },
    "done": true
  },
  "minecraft:recipes/redstone/dispenser": {
    "criteria": {
      "has_bow": "2025-01-31 22:56:40 -0300"
    },
    "done": true
  },
  "securitycraft:recipes/redstone/reinforced_dark_oak_fence_gate": {
    "criteria": {
      "has_stick": "2025-01-31 22:56:40 -0300"
    },
    "done": true
  },
  "securitycraft:recipes/building_blocks/secret_jungle_sign_item": {
    "criteria": {
      "has_sign": "2025-01-31 22:56:40 -0300"
    },
    "done": true
  },
  "securitycraft:recipes/building_blocks/secret_spruce_sign_item": {
    "criteria": {
      "has_sign": "2025-01-31 22:56:40 -0300"
    },
    "done": true
  },
  "mcwbridges:recipes/iron_bridge": {
    "criteria": {
      "has_planks": "2025-01-31 23:00:50 -0300"
    },
    "done": true
  },
  "mcwtrpdoors:recipes/jungle/jungle_paper_trapdoor": {
    "criteria": {
      "has_logs": "2025-01-31 22:56:40 -0300"
    },
    "done": true
  },
  "mcwtrpdoors:recipes/bamboo/bamboo_beach_trapdoor": {
    "criteria": {
      "has_logs": "2025-01-31 22:56:40 -0300"
    },
    "done": true
  },
  "securitycraft:recipes/misc/trophy_system": {
    "criteria": {
      "has_iron": "2025-01-31 23:00:50 -0300"
    },
    "done": true
  },
  "minecraft:recipes/brewing/cauldron": {
    "criteria": {
      "has_water_bucket": "2025-01-31 22:56:40 -0300"
    },
    "done": true
  },
  "minecraft:recipes/transportation/acacia_boat": {
    "criteria": {
      "in_water": "2025-01-31 22:57:37 -0300"
    },
    "done": true
  },
  "minecraft:recipes/redstone/iron_trapdoor": {
    "criteria": {
      "has_iron_ingot": "2025-01-31 23:00:50 -0300"
    },
    "done": true
  },
  "minecraft:recipes/decorations/jungle_fence": {
    "criteria": {
      "has_planks": "2025-01-31 23:14:00 -0300"
    },
    "done": true
  },
  "minecraft:recipes/building_blocks/chiseled_quartz_block_from_quartz_block_stonecutting": {
    "criteria": {
      "has_quartz_block": "2025-01-31 22:58:42 -0300"
    },
    "done": true
  },
  "farmersdelight:recipes/building_blocks/organic_compost_from_rotten_flesh": {
    "criteria": {
      "has_rotten_flesh": "2025-01-31 22:56:40 -0300"
    },
    "done": true
  },
  "minecraft:recipes/redstone/jungle_pressure_plate": {
    "criteria": {
      "has_planks": "2025-01-31 23:14:00 -0300"
    },
    "done": true
  },
  "minecraft:recipes/combat/wooden_sword": {
    "criteria": {
      "has_stick": "2025-01-31 22:56:40 -0300"
    },
    "done": true
  },
  "minecraft:recipes/tools/iron_axe": {
    "criteria": {
      "has_iron_ingot": "2025-01-31 23:00:50 -0300"
    },
    "done": true
  },
  "minecraft:recipes/building_blocks/quartz_slab_from_stonecutting": {
    "criteria": {
      "has_quartz_block": "2025-01-31 22:58:42 -0300"
    },
    "done": true
  },
  "mcwtrpdoors:recipes/jungle/jungle_barred_trapdoor": {
    "criteria": {
      "has_logs": "2025-01-31 22:56:40 -0300"
    },
    "done": true
  },
  "minecraft:recipes/combat/crossbow": {
    "criteria": {
      "has_iron_ingot": "2025-01-31 23:00:50 -0300"
    },
    "done": true
  },
  "minecraft:recipes/misc/iron_nugget_from_blasting": {
    "criteria": {
      "has_iron_shovel": "2025-01-31 22:56:40 -0300"
    },
    "done": true
  },
  "sophisticatedbackpacks:recipes/misc/gold_backpack": {
    "criteria": {
      "has_iron_backpack": "2025-01-31 22:56:40 -0300"
    },
    "done": true
  },
  "mcwbridges:recipes/bamboo_bridge_pier": {
    "criteria": {
      "has_planks": "2025-01-31 22:56:40 -0300"
    },
    "done": true
  },
  "minecraft:recipes/decorations/barrel": {
    "criteria": {
      "has_planks": "2025-01-31 23:14:00 -0300"
    },
    "done": true
  },
  "mcwbridges:recipes/bridge_torch": {
    "criteria": {
      "has_planks": "2025-01-31 22:56:40 -0300"
    },
    "done": true
  },
  "minecraft:recipes/combat/leather_boots": {
    "criteria": {
      "has_leather": "2025-01-31 22:56:40 -0300"
    },
    "done": true
  },
  "securitycraft:recipes/building_blocks/secret_bamboo_sign_item": {
    "criteria": {
      "has_sign": "2025-01-31 22:56:40 -0300"
    },
    "done": true
  },
  "minecraft:recipes/misc/stick_from_bamboo_item": {
    "criteria": {
      "has_bamboo": "2025-01-31 22:56:40 -0300"
    },
    "done": true
  },
  "mcwdoors:recipes/bamboo": {
    "criteria": {
      "has_wood": "2025-01-31 22:56:40 -0300"
    },
    "done": true
  },
  "securitycraft:recipes/misc/reinforced_birch_fence": {
    "criteria": {
      "has_stick": "2025-01-31 22:56:40 -0300"
    },
    "done": true
  },
  "farmersdelight:recipes/decorations/cutting_board": {
    "criteria": {
      "has_stick": "2025-01-31 22:56:40 -0300"
    },
    "done": true
  },
  "mcwlights:recipes/tiki_torches": {
    "criteria": {
      "has_wood": "2025-01-31 22:56:40 -0300"
    },
    "done": true
  },
  "securitycraft:recipes/misc/speed_module": {
    "criteria": {
      "has_iron": "2025-01-31 23:00:50 -0300"
    },
    "done": true
  },
  "minecraft:recipes/food/mushroom_stew": {
    "criteria": {
      "has_bowl": "2025-01-31 22:56:40 -0300"
    },
    "done": true
  },
  "mcwtrpdoors:recipes/bamboo/bamboo_mystic_trapdoor": {
    "criteria": {
      "has_logs": "2025-01-31 22:56:40 -0300"
    },
    "done": true
  },
  "securitycraft:recipes/misc/reinforced_dark_oak_fence": {
    "criteria": {
      "has_stick": "2025-01-31 22:56:40 -0300"
    },
    "done": true
  },
  "securitycraft:recipes/misc/reinforced_oak_fence": {
    "criteria": {
      "has_stick": "2025-01-31 22:56:40 -0300"
    },
    "done": true
  },
  "securitycraft:recipes/misc/camera_monitor": {
    "criteria": {
      "has_iron": "2025-01-31 23:00:50 -0300"
    },
    "done": true
  },
  "minecraft:recipes/building_blocks/bamboo_block": {
    "criteria": {
      "has_bamboo": "2025-01-31 22:56:40 -0300"
    },
    "done": true
  },
  "farmersdelight:recipes/combat/iron_knife": {
    "criteria": {
      "has_iron_ingot": "2025-01-31 23:00:50 -0300"
    },
    "done": true
  },
  "securitycraft:recipes/redstone/reinforced_oak_fence_gate": {
    "criteria": {
      "has_stick": "2025-01-31 22:56:40 -0300"
    },
    "done": true
  },
  "securitycraft:recipes/misc/sc_manual": {
    "criteria": {
      "has_wood": "2025-01-31 22:56:40 -0300"
    },
    "done": true
  },
  "securitycraft:recipes/building_blocks/secret_oak_hanging_sign": {
    "criteria": {
      "has_sign": "2025-01-31 22:56:40 -0300"
    },
    "done": true
  },
  "mcwtrpdoors:recipes/jungle/jungle_blossom_trapdoor": {
    "criteria": {
      "has_plankss": "2025-01-31 23:14:00 -0300"
    },
    "done": true
  },
  "mcwtrpdoors:recipes/bamboo_trapdoor": {
    "criteria": {
      "has_logs": "2025-01-31 22:56:40 -0300"
    },
    "done": true
  },
  "securitycraft:recipes/building_blocks/secret_acacia_hanging_sign": {
    "criteria": {
      "has_sign": "2025-01-31 22:56:40 -0300"
    },
    "done": true
  },
  "securitycraft:recipes/misc/redstone_module": {
    "criteria": {
      "has_iron": "2025-01-31 23:00:50 -0300"
    },
    "done": true
  },
  "securitycraft:recipes/misc/reinforced_bamboo_fence": {
    "criteria": {
      "has_stick": "2025-01-31 22:56:40 -0300"
    },
    "done": true
  },
  "mcwtrpdoors:recipes/bamboo/bamboo_blossom_trapdoor": {
    "criteria": {
      "has_plankss": "2025-01-31 22:56:40 -0300"
    },
    "done": true
  },
  "sophisticatedbackpacks:recipes/misc/iron_backpack_from_copper": {
    "criteria": {
      "has_copper_backpack": "2025-01-31 22:56:40 -0300"
    },
    "done": true
  },
  "minecraft:recipes/decorations/scaffolding": {
    "criteria": {
      "has_bamboo": "2025-01-31 22:56:40 -0300"
    },
    "done": true
  },
  "mcwbridges:recipes/pliers": {
    "criteria": {
      "has_planks": "2025-01-31 23:00:50 -0300"
    },
    "done": true
  },
  "securitycraft:recipes/misc/reinforced_crimson_fence": {
    "criteria": {
      "has_stick": "2025-01-31 22:56:40 -0300"
    },
    "done": true
  },
  "mcwfurnitures:recipes/jungle": {
    "criteria": {
      "has_wood": "2025-01-31 22:56:40 -0300"
    },
    "done": true
  },
  "securitycraft:recipes/misc/door_indestructible_iron_item": {
    "criteria": {
      "has_iron": "2025-01-31 23:00:50 -0300"
    },
    "done": true
  },
  "securitycraft:recipes/misc/reinforced_spruce_fence": {
    "criteria": {
      "has_stick": "2025-01-31 22:56:40 -0300"
    },
    "done": true
  },
  "minecraft:recipes/building_blocks/jungle_slab": {
    "criteria": {
      "has_planks": "2025-01-31 23:14:00 -0300"
    },
    "done": true
  },
  "mcwlights:recipes/lantern": {
    "criteria": {
      "has_wood": "2025-01-31 22:56:40 -0300"
    },
    "done": true
  },
  "minecraft:recipes/redstone/iron_door": {
    "criteria": {
      "has_iron_ingot": "2025-01-31 23:00:50 -0300"
    },
    "done": true
  },
  "securitycraft:recipes/tools/universal_block_remover": {
    "criteria": {
      "has_iron": "2025-01-31 23:00:50 -0300"
    },
    "done": true
  },
  "minecraft:recipes/transportation/jungle_boat": {
    "criteria": {
      "in_water": "2025-01-31 22:57:37 -0300"
    },
    "done": true
  },
  "securitycraft:recipes/building_blocks/secret_sign_item": {
    "criteria": {
      "has_sign": "2025-01-31 22:56:40 -0300"
    },
    "done": true
  },
  "mcwwindows:recipes/jungle": {
    "criteria": {
      "has_wood": "2025-01-31 22:56:40 -0300"
    },
    "done": true
  },
  "minecraft:recipes/redstone/heavy_weighted_pressure_plate": {
    "criteria": {
      "has_iron_ingot": "2025-01-31 23:00:50 -0300"
    },
    "done": true
  },
  "minecraft:recipes/transportation/dark_oak_boat": {
    "criteria": {
      "in_water": "2025-01-31 22:57:37 -0300"
    },
    "done": true
  },
  "mcwlights:recipes/garden_light": {
    "criteria": {
      "has_wood": "2025-01-31 23:00:50 -0300"
    },
    "done": true
  },
  "securitycraft:recipes/building_blocks/secret_spruce_hanging_sign": {
    "criteria": {
      "has_sign": "2025-01-31 22:56:40 -0300"
    },
    "done": true
  },
  "DataVersion": 3465
}